batou_scm/__init__.py
batou_scm/buildout.py
batou_scm/conftest.py
batou_scm/source.py
batou_scm/resources/buildout_overrides.cfg
batou_scm/resources/hgrc
batou_scm/tests/__init__.py
batou_scm/tests/test_buildout.py
batou_scm/tests/test_source.py
batou_scm-1.1.dist-info/LICENSE.txt
batou_scm-1.1.dist-info/METADATA
batou_scm-1.1.dist-info/WHEEL
batou_scm-1.1.dist-info/entry_points.txt
batou_scm-1.1.dist-info/top_level.txt
batou_scm-1.1.dist-info/RECORD
