Metadata-Version: 2.1
Name: batou-scm
Version: 1.1
Summary: Batou components for managing source code in a development deployment.
Home-page: https://github.com/gocept/batou_scm
Author: gocept <mail@gocept.com>
Author-email: mail@gocept.com
License: ZPL 2.1
Keywords: batou source code development checkout clone buildout
Platform: UNKNOWN
Classifier: Development Status :: 5 - Production/Stable
Classifier: Intended Audience :: Developers
Classifier: License :: OSI Approved :: Zope Public License
Classifier: Operating System :: OS Independent
Classifier: Programming Language :: Python
Classifier: Programming Language :: Python :: 3
Classifier: Programming Language :: Python :: 3.6
Classifier: Programming Language :: Python :: 3.7
Classifier: Programming Language :: Python :: 3.8
Classifier: Programming Language :: Python :: 3.9
Classifier: Topic :: Software Development :: Build Tools
Requires-Python: >=3.6, <4
Requires-Dist: batou (>=2)
Provides-Extra: test
Requires-Dist: mock ; extra == 'test'
